databricks_generic_tools/__init__.py
databricks_generic_tools/connectors.py
databricks_generic_tools/databricks_extension.py
databricks_generic_tools/datetime_extension.py
databricks_generic_tools/debugprinter.py
databricks_generic_tools/json_extension.py
databricks_generic_tools/parquet_extension.py
databricks_generic_tools/sparksql.py
databricks_generic_tools/sql.py
databricks_generic_tools/widget_extension.py
databricks_generic_tools/zip_extension.py
databricks_generic_tools-0.1.1.dist-info/METADATA
databricks_generic_tools-0.1.1.dist-info/WHEEL
databricks_generic_tools-0.1.1.dist-info/top_level.txt
databricks_generic_tools-0.1.1.dist-info/RECORD
