Metadata-Version: 2.4
Name: databricks_generic_tools
Version: 0.1.1
Summary: Contains generic tools for Databricks, such as connectors and debug printers.
Author-email: Alpina Group NL - Data Team <data@alpinagroup.com>
Requires-Python: >=3.12
Requires-Dist: pyodbc
Requires-Dist: pyarrow
Requires-Dist: pyspark
Requires-Dist: pyspark.sql
Requires-Dist: mypy
Requires-Dist: databricks-connect
